niceutils/__init__.py
niceutils/niceutils.py
niceutils-0.1.0.dist-info/AUTHORS.rst
niceutils-0.1.0.dist-info/METADATA
niceutils-0.1.0.dist-info/WHEEL
niceutils-0.1.0.dist-info/top_level.txt
niceutils-0.1.0.dist-info/RECORD
