Metadata-Version: 2.1
Name: niceutils
Version: 0.1.0
Summary: niceutils things for Developing python stuff
Home-page: https://github.com/scottnelson/niceutils
Author: Scott Nelson
Author-email: scott.nelson@onepeloton.com
License: UNKNOWN
Keywords: niceutils
Platform: UNKNOWN
Classifier: Development Status :: 2 - Pre-Alpha
Classifier: Intended Audience :: Developers
Classifier: Natural Language :: English
Classifier: Programming Language :: Python :: 3
Classifier: Programming Language :: Python :: 3.5
Classifier: Programming Language :: Python :: 3.6
Classifier: Programming Language :: Python :: 3.7
Classifier: Programming Language :: Python :: 3.8
Requires-Python: >=3.5
